pychunker/__init__.py
pychunker/chunk.py
pychunker/chunker.py
pychunker/chunker.pyi
pychunker/chunkfile.py
pychunker/crc.py
pychunker/exceptions.py
pychunker/functional.py
pychunker/functional.pyi
pychunker/types.py
pychunker/units.py
pychunker-1.4.1.dist-info/LICENSE
pychunker-1.4.1.dist-info/METADATA
pychunker-1.4.1.dist-info/WHEEL
pychunker-1.4.1.dist-info/RECORD
