Metadata-Version: 2.1
Name: pychunker
Version: 1.4.1
Summary: Module for reading/writing chunk files.
Home-page: https://github.com/romanin-rf/pychunker
License: MIT
Keywords: pychunker,chunker,chunkfile,io,file,chunk,read,write
Author: Romanin
Author-email: semina054@gmail.com
Requires-Python: >=3.6
Classifier: License :: OSI Approved :: MIT License
Classifier: Operating System :: OS Independent
Classifier: Programming Language :: Python :: 3
Classifier: Programming Language :: Python :: 3.6
Classifier: Programming Language :: Python :: 3.7
Classifier: Programming Language :: Python :: 3.8
Classifier: Programming Language :: Python :: 3.9
Classifier: Programming Language :: Python :: 3.10
Classifier: Programming Language :: Python :: 3.11
Classifier: Programming Language :: Python :: 3.12
Classifier: Topic :: System :: Filesystems
Project-URL: Repository, https://github.com/romanin-rf/pychunker
